CHANGES.txt
CONTRIBUTORS.txt
MANIFEST.in
README.txt
bootstrap.py
buildout.cfg
ffmpeg.cfg
setup.cfg
setup.py
versions.cfg
docs/INSTALL.txt
docs/LICENSE.GPL
docs/LICENSE.txt
patches/async.patch
plumi/__init__.py
plumi.content.egg-info/PKG-INFO
plumi.content.egg-info/SOURCES.txt
plumi.content.egg-info/dependency_links.txt
plumi.content.egg-info/entry_points.txt
plumi.content.egg-info/namespace_packages.txt
plumi.content.egg-info/not-zip-safe
plumi.content.egg-info/requires.txt
plumi.content.egg-info/top_level.txt
plumi/content/README.txt
plumi/content/__init__.py
plumi/content/adapters.py
plumi/content/config.py
plumi/content/configure.zcml
plumi/content/convertBMP.py
plumi/content/indexes.py
plumi/content/metadataextractor.py
plumi/content/permissions.py
plumi/content/plumi.content-default.txt
plumi/content/setuphandlers.py
plumi/content/subscribers.py
plumi/content/testing.py
plumi/content/version.txt
plumi/content/vocabs.py
plumi/content/browser/RSS.pt
plumi/content/browser/__init__.py
plumi/content/browser/adapters.py
plumi/content/browser/brain_rendering.py
plumi/content/browser/callout.py
plumi/content/browser/configure.zcml
plumi/content/browser/controlpanel.py
plumi/content/browser/download.py
plumi/content/browser/download_torrent.py
plumi/content/browser/featured_videos.py
plumi/content/browser/forms.py
plumi/content/browser/interfaces.py
plumi/content/browser/reTranscode.pt
plumi/content/browser/reTranscode.py
plumi/content/browser/rssview.py
plumi/content/browser/taxonomy.py
plumi/content/browser/upload.py
plumi/content/browser/video.py
plumi/content/browser/videos_listing.py
plumi/content/browser/forms_templates/ccwidget.pt
plumi/content/browser/forms_templates/videoaddform.pt
plumi/content/browser/images/clip_default.png
plumi/content/browser/images/step1_off.gif
plumi/content/browser/images/step1_on.gif
plumi/content/browser/images/step2_off.gif
plumi/content/browser/images/step2_on.gif
plumi/content/browser/images/step3_off.gif
plumi/content/browser/images/step3_on.gif
plumi/content/browser/images/blueimp-jQuery-File-Upload-2bc9a5f/.DS_Store
plumi/content/browser/images/blueimp-jQuery-File-Upload-2bc9a5f/.gitignore
plumi/content/browser/images/blueimp-jQuery-File-Upload-2bc9a5f/README.md
