Metadata-Version: 1.0
Name: plumi.content
Version: 4.5
Summary: Plumi Content Types Product
Home-page: https://github.com/plumi/plumi.content
Author: Andy Nicholson
Author-email: andy@infiniterecursion.com.au
License: GPL
Keywords: plone plumi content
Platform: UNKNOWN
Classifier: Framework :: Plone
Classifier: Intended Audience :: Developers
Classifier: Topic :: Software Development :: Libraries :: Python Modules
Classifier: License :: OSI Approved :: GNU General Public License (GPL)
Classifier: Environment :: Web Environment
Classifier: Programming Language :: Python
